dns_cache/__init__.py
dns_cache/block.py
dns_cache/disk_dict.py
dns_cache/diskcache.py
dns_cache/dnspython.py
dns_cache/expiration.py
dns_cache/hosts.py
dns_cache/key_transform.py
dns_cache/persistence.py
dns_cache/pickle.py
dns_cache/resolver.py
dns_cache/sqlitedict.py
dns_cache/stash.py
dns_cache-0.3.0.dist-info/LICENSE
dns_cache-0.3.0.dist-info/METADATA
dns_cache-0.3.0.dist-info/WHEEL
dns_cache-0.3.0.dist-info/top_level.txt
dns_cache-0.3.0.dist-info/version.txt
dns_cache-0.3.0.dist-info/RECORD
